variance_scheduler/__init__.py
variance_scheduler/abs_var_scheduler.py
variance_scheduler/cosine.py
variance_scheduler/hyperbolic_secant.py
variance_scheduler/linear.py
ddpm-1.0.0.dist-info/METADATA
ddpm-1.0.0.dist-info/WHEEL
ddpm-1.0.0.dist-info/top_level.txt
ddpm-1.0.0.dist-info/RECORD
