Metadata-Version: 2.1
Name: ddpm
Version: 1.0.0
Summary: Pytorch implementation of 'Improved Denoising Diffusion Probabilistic Models', 'Denoising Diffusion Probabilistic Models' and 'Classifier-free Diffusion Guidance'
License: MIT
Keywords: pytorch,ddpm,denoising diffusion probabilistic model,generative
Classifier: Development Status :: 5 - Production/Stable
Classifier: Intended Audience :: Developers
Classifier: Intended Audience :: Science/Research
Classifier: License :: OSI Approved :: MIT License
Classifier: Operating System :: OS Independent
Classifier: Programming Language :: Python
Classifier: Programming Language :: Python :: 3
Classifier: Programming Language :: Python :: 3.7
Classifier: Programming Language :: Python :: 3.8
Classifier: Programming Language :: Python :: 3.9
Classifier: Programming Language :: Python :: 3.10
Classifier: Topic :: Scientific/Engineering :: Artificial Intelligence
Classifier: Topic :: Software Development :: Libraries :: Python Modules
Requires-Python: <3.10,>=3.7
Requires-Dist: torch (>=1.8)
Requires-Dist: pytorch-lightning (>=1.8)
Requires-Dist: torchvision
Requires-Dist: tensorguard (==1.0.0)
Requires-Dist: path (>=16.0)
Provides-Extra: dev
Requires-Dist: pytest ; extra == 'dev'
